langchain_visualizer/__init__.py
langchain_visualizer/agents/__init__.py
langchain_visualizer/agents/tools.py
langchain_visualizer/chains/__init__.py
langchain_visualizer/chains/base.py
langchain_visualizer/embeddings/__init__.py
langchain_visualizer/hijacking.py
langchain_visualizer/ice.py
langchain_visualizer/jupyter.py
langchain_visualizer/llms/__init__.py
langchain_visualizer/llms/base.py
langchain_visualizer/prompts/__init__.py
langchain_visualizer/prompts/few_shot.py
langchain_visualizer/prompts/prompt.py
langchain_visualizer/py.typed
langchain_visualizer/visualize.py
langchain_visualizer-0.0.33.dist-info/LICENSE
langchain_visualizer-0.0.33.dist-info/METADATA
langchain_visualizer-0.0.33.dist-info/WHEEL
langchain_visualizer-0.0.33.dist-info/RECORD
