Metadata-Version: 2.1
Name: langchain-visualizer
Version: 0.0.33
Summary: Visualization and debugging tool for LangChain workflows
Author: Amos Jun-yeung Ng
Author-email: me@amos.ng
Requires-Python: >=3.9,<4.0
Classifier: Programming Language :: Python :: 3
Classifier: Programming Language :: Python :: 3.9
Classifier: Programming Language :: Python :: 3.10
Classifier: Programming Language :: Python :: 3.11
Requires-Dist: fvalues (>=0.0.4,<0.0.5)
Requires-Dist: gorilla (>=0.4.0,<0.5.0)
Requires-Dist: langchain (>=0.0.344,<0.1)
Requires-Dist: ought-ice (>=0.5.0,<0.6.0)
Requires-Dist: pydantic (>=1.0.0,<2.0.0)
